windows_snake_game/__init__.py
windows_snake_game-0.1.11.dist-info/licenses/LICENSE.txt
windows_snake_game-0.1.11.dist-info/METADATA
windows_snake_game-0.1.11.dist-info/WHEEL
windows_snake_game-0.1.11.dist-info/top_level.txt
windows_snake_game-0.1.11.dist-info/RECORD
